{
	"lamp1" :{
		"r" : 123,
		"g" : 42,
		"b" : 0,
		"l" : 0
	},
	"lamp2" :{
		"r" : 0,
		"g" : 0,
		"b" : 255,
		"l" : 0
	},
	"lamp3" :{
		"r" : 255,
		"g" : 0,
		"b" : 0,
		"l" : 0
	},
	"lamp4" :{
		"r" : 0,
		"g" : 255,
		"b" : 0,
		"l" : 0
	},
	"lamp5" :{
		"r" : 0,
		"g" : 0,
		"b" : 0,
		"l" : 0
	},
	"lamp6" :{
		"r" : 0,
		"g" : 0,
		"b" : 0,
		"l" : 0
	},
	"lamp7" :{
		"r" : 0,
		"g" : 0,
		"b" : 0,
		"l" : 0
	},
	"lamp8" :{
		"r" : 0,
		"g" : 0,
		"b" : 0,
		"l" : 0
	},
	"lamp9" :{
		"r" : 0,
		"g" : 0,
		"b" : 0,
		"l" : 0
	},
	"lamp10" :{
		"r" : 0,
		"g" : 0,
		"b" : 0,
		"l" : 0
	},
	"lamp11" :{
		"r" : 0,
		"g" : 0,
		"b" : 0,
		"l" : 0
	},
	"lamp12" :{
		"r" : 0,
		"g" : 0,
		"b" : 0,
		"l" : 0
	},
	"lamp13" :{
		"r" : 0,
		"g" : 0,
		"b" : 0,
		"l" : 0
	},
	"lamp14" :{
		"r" : 0,
		"g" : 0,
		"b" : 0,
		"l" : 0
	},
	"lamp15" :{
		"r" : 0,
		"g" : 0,
		"b" : 0,
		"l" : 0
	},
	"lamp16" :{
		"r" : 0,
		"g" : 0,
		"b" : 0,
		"l" : 0
	},
	"lamp17" :{
		"r" : 0,
		"g" : 0,
		"b" : 0,
		"l" : 0
	},
	"lamp18" :{
		"r" : 0,
		"g" : 0,
		"b" : 0,
		"l" : 0
	},
	"lamp19" :{
		"r" : 0,
		"g" : 0,
		"b" : 0,
		"l" : 0
	},
	"lamp20" :{
		"r" : 0,
		"g" : 0,
		"b" : 0,
		"l" : 0
	},
	"lamp21" :{
		"r" : 0,
		"g" : 0,
		"b" : 0,
		"l" : 0
	},
	"lamp22" :{
		"r" : 0,
		"g" : 0,
		"b" : 0,
		"l" : 0
	},
	"lamp23" :{
		"r" : 0,
		"g" : 0,
		"b" : 0,
		"l" : 0
	},
	"lamp24" :{
		"r" : 0,
		"g" : 0,
		"b" : 0,
		"l" : 0
	},
	"lamp25" :{
		"r" : 0,
		"g" : 0,
		"b" : 0,
		"l" : 0
	},
	"lamp26" :{
		"r" : 0,
		"g" : 0,
		"b" : 0,
		"l" : 0
	},
	"lamp27" :{
		"r" : 0,
		"g" : 0,
		"b" : 0,
		"l" : 0
	},
	"lamp28" :{
		"r" : 0,
		"g" : 0,
		"b" : 0,
		"l" : 0
	},
	"lamp29" :{
		"r" : 0,
		"g" : 0,
		"b" : 0,
		"l" : 0
	},
	"lamp30" :{
		"r" : 0,
		"g" : 0,
		"b" : 0,
		"l" : 0
	},
	"lamp31" :{
		"r" : 0,
		"g" : 0,
		"b" : 0,
		"l" : 0
	},
	"lamp32" :{
		"r" : 0,
		"g" : 0,
		"b" : 0,
		"l" : 0
	}
}